nltk/__init__.py
nltk/hello.py
rd_lab_nltk-0.0.1.dist-info/METADATA
rd_lab_nltk-0.0.1.dist-info/WHEEL
rd_lab_nltk-0.0.1.dist-info/top_level.txt
rd_lab_nltk-0.0.1.dist-info/RECORD
