Metadata-Version: 2.1
Name: rd-lab-nltk
Version: 0.0.1
Summary: Streaming video data via networks
Author: Soy Vitou (RUPP)
Author-email: <soyvitoupro@gmail.com>
Keywords: python
Classifier: Development Status :: 1 - Planning
Classifier: Intended Audience :: Developers
Classifier: Programming Language :: Python :: 3
Classifier: Operating System :: Unix
Classifier: Operating System :: MacOS :: MacOS X
Classifier: Operating System :: Microsoft :: Windows
